django_template_lsp-1.2.2.dist-info/licenses/LICENSE
djlsp/__init__.py
djlsp/__main__.py
djlsp/cli.py
djlsp/constants.py
djlsp/index.py
djlsp/parser.py
djlsp/server.py
djlsp/scripts/django-collector.py
django_template_lsp-1.2.2.dist-info/METADATA
django_template_lsp-1.2.2.dist-info/WHEEL
django_template_lsp-1.2.2.dist-info/entry_points.txt
django_template_lsp-1.2.2.dist-info/top_level.txt
django_template_lsp-1.2.2.dist-info/RECORD
