Metadata-Version: 2.4
Name: django-template-lsp
Version: 1.2.2
Summary: Django template LSP
Author-email: Four Digits <info@fourdigits.nl>
License:                     GNU GENERAL PUBLIC LICENSE
Project-URL: Homepage, https://github.com/fourdigits/django-template-lsp
Keywords: django,template,lsp,python
Classifier: Environment :: Web Environment
Classifier: Framework :: Django
Classifier: Intended Audience :: Developers
Classifier: License :: OSI Approved :: GNU General Public License v3 (GPLv3)
Classifier: Programming Language :: Python
Classifier: Programming Language :: Python :: 3.9
Classifier: Programming Language :: Python :: 3.10
Classifier: Programming Language :: Python :: 3.11
Classifier: Programming Language :: Python :: 3.12
Requires-Python: >=3.9
License-File: LICENSE
Requires-Dist: pygls<2.0.0,>=1.0.0
Requires-Dist: jedi
Provides-Extra: dev
Requires-Dist: tox; extra == "dev"
Requires-Dist: black; extra == "dev"
Requires-Dist: isort; extra == "dev"
Requires-Dist: flake8; extra == "dev"
Requires-Dist: flake8-pyproject; extra == "dev"
Requires-Dist: pytest; extra == "dev"
Requires-Dist: pytest-check; extra == "dev"
Requires-Dist: pytest-cov; extra == "dev"
Dynamic: license-file
